LICENSE
MANIFEST.in
README.md
setup.py
pyalphaclock/__init__.py
pyalphaclock.egg-info/PKG-INFO
pyalphaclock.egg-info/SOURCES.txt
pyalphaclock.egg-info/dependency_links.txt
pyalphaclock.egg-info/pbr.json
pyalphaclock.egg-info/requires.txt
pyalphaclock.egg-info/top_level.txt