Metadata-Version: 1.0
Name: pyalphaclock
Version: 0.1
Summary: Python library for interacting with the Alpha Clock Five
Home-page: https://github.com/agermanidis/pyalphaclock
Author: Anastasis Germanidis
Author-email: agermanidis@gmail.com
License: The MIT License (MIT)
